django_updater-0.5.0.dist-info/DESCRIPTION.rst
django_updater-0.5.0.dist-info/METADATA
django_updater-0.5.0.dist-info/metadata.json
django_updater-0.5.0.dist-info/pbr.json
django_updater-0.5.0.dist-info/RECORD
django_updater-0.5.0.dist-info/top_level.txt
django_updater-0.5.0.dist-info/WHEEL
updater/__init__.py
updater/admin.py
updater/apps.py
updater/check.py
updater/conf.py
updater/models.py
updater/package.py
updater/register.py
updater/tasks.py
updater/urls.py
updater/util.py
updater/views.py
updater/management/__init__.py
updater/management/commands/__init__.py
updater/management/commands/check_for_updates.py
updater/management/commands/register_updater.py
updater/migrations/0001_initial.py
updater/migrations/0001_squashed_0005_auto_20151013_1152.py
updater/migrations/0002_notification.py
updater/migrations/0003_auto_20150923_0854.py
updater/migrations/0004_auto_20150923_1230.py
updater/migrations/0005_auto_20151013_1152.py
updater/migrations/__init__.py
updater/south_migrations/0001_initial.py
updater/south_migrations/__init__.py
updater/static/updater/ajax-loader.gif
updater/templates/admin_banner.html
updater/templates/mail.html
updater/templates/mail.txt
updater/templates/security_issues.txt
updater/templates/summary.html
updater/templates/summary.txt
updater/templates/admin/base_site.html
updater/templates/admin/registration.html
updater/templates/admin/status.html
