Metadata-Version: 2.0
Name: django-updater
Version: 0.5.0
Summary: Helps you to keep your Django installation up to date
Home-page: https://github.com/jayfk/django-updater
Author: Jannis Gebauer
Author-email: ja.geb@me.com
License: BSD
Keywords: django-updater
Platform: UNKNOWN
Classifier: Development Status :: 2 - Pre-Alpha
Classifier: Framework :: Django
Classifier: Intended Audience :: Developers
Classifier: License :: OSI Approved :: BSD License
Classifier: Natural Language :: English
Classifier: Programming Language :: Python :: 2
Classifier: Programming Language :: Python :: 2.7
Classifier: Programming Language :: Python :: 3
Classifier: Programming Language :: Python :: 3.3
Classifier: Programming Language :: Python :: 3.4
Requires-Dist: django
Requires-Dist: requests
Requires-Dist: pip
